pypwrctrl/__init__.py
pypwrctrl/main.py
pypwrctrl/pypwrctrl.py
pypwrctrl-0.2.2.dist-info/LICENSE
pypwrctrl-0.2.2.dist-info/METADATA
pypwrctrl-0.2.2.dist-info/WHEEL
pypwrctrl-0.2.2.dist-info/entry_points.txt
pypwrctrl-0.2.2.dist-info/top_level.txt
pypwrctrl-0.2.2.dist-info/RECORD
