Metadata-Version: 2.1
Name: pypwrctrl
Version: 0.2.2
Summary: Anel NET-PwrCtrl library and command line utility
Home-page: https://github.com/thammi/pypwrctrl
Author: Thammi
Author-email: thammi@chaossource.net
License: GPLv3
Keywords: net-pwrctrl anel
Platform: UNKNOWN
Classifier: Development Status :: 4 - Beta
Classifier: License :: OSI Approved :: GNU General Public License v3 (GPLv3)
Classifier: Natural Language :: English
Classifier: Environment :: Console
Classifier: Programming Language :: Python :: 3
Classifier: Intended Audience :: Developers
Classifier: Intended Audience :: System Administrators
Classifier: Intended Audience :: End Users/Desktop
Classifier: Topic :: Home Automation
Classifier: Topic :: Utilities
